{
  "colorPalette": {
    "primary": "#00AEEF",
    "secondary": "#FDC82F",
    "background": "#0D1B2A",
    "surface": "rgba(22, 33, 62, 0.85)",
    "accent": "#FF4B2B"
  },
  "typography": {
    "headingFont": "Orbitron, sans-serif",
    "bodyFont": "Inter, sans-serif"
  },
  "uiPatterns": {
    "borderRadius": "2px",
    "shadows": "0 0 15px rgba(0, 174, 239, 0.4)",
    "spacing": "16px",
    "borderWidth": "3px"
  },
  "vibeKeywords": [
    "Live-Broadcast",
    "Kattelox-Island",
    "High-Energy",
    "Sleek-Motion",
    "Sporting-Event"
  ]
}